easy_whisperx/__init__.py
easy_whisperx/aligner.py
easy_whisperx/base_model.py
easy_whisperx/bulk_executor.py
easy_whisperx/diarizer.py
easy_whisperx/performance.py
easy_whisperx/py.typed
easy_whisperx/transcriber.py
easy_whisperx/utils.py
easy_whisperx-0.0.8.dist-info/METADATA
easy_whisperx-0.0.8.dist-info/WHEEL
easy_whisperx-0.0.8.dist-info/top_level.txt
easy_whisperx-0.0.8.dist-info/RECORD
