Metadata-Version: 2.4
Name: easy-whisperx
Version: 0.0.8
Summary: A Python package for easy transcription using WhisperX.
Author-email: Aryan Falahtpisheh <aryanfalahat@gmail.com>
License: BSD-2-Clause
Project-URL: Homepage, https://github.com/falahat/easy-whisperx
Project-URL: Repository, https://github.com/falahat/easy-whisperx.git
Project-URL: Issues, https://github.com/falahat/easy-whisperx/issues
Keywords: whisperx,transcription,audio,speech-to-text
Classifier: Development Status :: 4 - Beta
Classifier: Intended Audience :: Developers
Classifier: License :: OSI Approved :: MIT License
Classifier: Programming Language :: Python :: 3
Classifier: Programming Language :: Python :: 3.10
Classifier: Programming Language :: Python :: 3.11
Classifier: Programming Language :: Python :: 3.12
Requires-Python: <3.13,>=3.10
Requires-Dist: numpy
Requires-Dist: torch
Requires-Dist: pydub
Requires-Dist: pandas
Requires-Dist: whisperx-typed>=3.4.5
Requires-Dist: whisperx-stubs>=3.4.5
Provides-Extra: dev
Requires-Dist: pytest>=6.0.0; extra == "dev"
Requires-Dist: pytest-cov>=2.0.0; extra == "dev"
Requires-Dist: mypy>=1.0.0; extra == "dev"
Requires-Dist: black>=22.0.0; extra == "dev"
Requires-Dist: flake8>=4.0.0; extra == "dev"
Requires-Dist: coverage; extra == "dev"
Provides-Extra: notebook
Requires-Dist: jupyter>=1.0.0; extra == "notebook"
Requires-Dist: pandas; extra == "notebook"
Requires-Dist: matplotlib; extra == "notebook"
